rbtools/__init__.py
rbtools/deprecation.py
rbtools/api/__init__.py
rbtools/api/cache.py
rbtools/api/capabilities.py
rbtools/api/client.py
rbtools/api/decode.py
rbtools/api/decorators.py
rbtools/api/errors.py
rbtools/api/factory.py
rbtools/api/request.py
rbtools/api/resource.py
rbtools/api/utils.py
rbtools/api/tests/__init__.py
rbtools/api/tests/base.py
rbtools/api/tests/test_capabilities.py
rbtools/api/tests/test_errors.py
rbtools/api/tests/test_factory.py
rbtools/api/tests/test_http_request.py
rbtools/api/tests/test_resource.py
rbtools/api/transport/__init__.py
rbtools/api/transport/sync.py
rbtools/clients/__init__.py
rbtools/clients/bazaar.py
rbtools/clients/clearcase.py
rbtools/clients/cvs.py
rbtools/clients/errors.py
rbtools/clients/git.py
rbtools/clients/mercurial.py
rbtools/clients/perforce.py
rbtools/clients/plastic.py
rbtools/clients/sos.py
rbtools/clients/svn.py
rbtools/clients/tfs.py
rbtools/clients/base/__init__.py
rbtools/clients/base/patch.py
rbtools/clients/base/registry.py
rbtools/clients/base/repository.py
rbtools/clients/base/scmclient.py
rbtools/clients/tests/__init__.py
rbtools/clients/tests/test_base_scmclient.py
rbtools/clients/tests/test_bzr.py
rbtools/clients/tests/test_clearcase.py
rbtools/clients/tests/test_cvs.py
rbtools/clients/tests/test_git.py
rbtools/clients/tests/test_legacy_patcher.py
rbtools/clients/tests/test_mercurial.py
rbtools/clients/tests/test_p4.py
rbtools/clients/tests/test_plastic.py
rbtools/clients/tests/test_scanning.py
rbtools/clients/tests/test_scmclient_registry.py
rbtools/clients/tests/test_sos.py
rbtools/clients/tests/test_svn.py
rbtools/clients/tests/test_tfs.py
rbtools/clients/tests/testdata/cvs-repo/CVSROOT/checkoutlist
"rbtools/clients/tests/testdata/cvs-repo/CVSROOT/checkoutlist,v"
rbtools/clients/tests/testdata/cvs-repo/CVSROOT/commitinfo
"rbtools/clients/tests/testdata/cvs-repo/CVSROOT/commitinfo,v"
rbtools/clients/tests/testdata/cvs-repo/CVSROOT/config
rbtools-5.3.dist-info/licenses/AUTHORS
rbtools-5.3.dist-info/licenses/COPYING
rbtools-5.3.dist-info/METADATA
rbtools-5.3.dist-info/WHEEL
rbtools-5.3.dist-info/entry_points.txt
rbtools-5.3.dist-info/top_level.txt
rbtools-5.3.dist-info/RECORD
