Metadata-Version: 2.4
Name: RBTools
Version: 5.3
Summary: Command line tools and API for working with code and document reviews on Review Board
Author-email: "Beanbag, Inc." <questions@beanbaginc.com>
License: MIT
Project-URL: homepage, https://www.reviewboard.org/downloads/rbtools/
Project-URL: documentation, https://www.reviewboard.org/docs/rbtools/
Project-URL: repository, https://github.com/reviewboard/rbtools
Classifier: Development Status :: 5 - Production/Stable
Classifier: Environment :: Console
Classifier: Framework :: Review Board
Classifier: Intended Audience :: Developers
Classifier: License :: OSI Approved :: MIT License
Classifier: Natural Language :: English
Classifier: Operating System :: OS Independent
Classifier: Programming Language :: Python
Classifier: Programming Language :: Python :: 3
Classifier: Programming Language :: Python :: 3.8
Classifier: Programming Language :: Python :: 3.9
Classifier: Programming Language :: Python :: 3.10
Classifier: Programming Language :: Python :: 3.11
Classifier: Programming Language :: Python :: 3.12
Classifier: Topic :: Software Development
Classifier: Topic :: Software Development :: Quality Assurance
Requires-Python: >=3.8
License-File: COPYING
License-File: AUTHORS
Requires-Dist: certifi>=2023.5.7
Requires-Dist: colorama
Requires-Dist: housekeeping~=1.1
Requires-Dist: packaging>=21.3
Requires-Dist: puremagic
Requires-Dist: pydiffx~=1.1.0
Requires-Dist: texttable
Requires-Dist: typing_extensions>=4.3.0
Requires-Dist: tqdm
Requires-Dist: importlib-metadata>=5.0
Requires-Dist: importlib-resources>=5.9
Dynamic: license-file
